ALU/ALUE03.v
//Laboratorio 8 - Electrónica digital
//Diego Eestrada 19264

//Ejercicio 03
//ALU


module ALU(
    input wire [3:0]m, 
    input wire [3:0]n, 
    input wire [2:0]com,
    output reg [3:0]r); 


        always @ (m or n or com) begin

            case(com)
                3'b000: r = m & n;  
                3'b001: r = m | n; 
                3'b010: r = m + n; 
                3'b100: r = m & ~n;
                3'b101: r = m | ~n;
                3'b110: r = m - n; 
                3'b111: r = (m < n) ? 1:0; 
                default: r = 4'b0000; 
            endcase
        end
endmodule

ALU/ALUE03_tb.v
module testbench();

reg [3:0]m;
reg [3:0]n;
reg [2:0]com;
wire [3:0]r;

ALU test(m, n, com, r);

initial begin
    #1
    $display("-ALU-");
    $display("m n com       r");
    $monitor("%b %b %b      %b", m, n, com, r);
        m = 4'b0000; n = 4'b0000; com = 3'b000;
    #1 m = 4'b0001; n = 4'b0001; com = 3'b000;
    #1 m = 4'b0001; n = 4'b0001; com = 3'b001;
    #1 m = 4'b0001; n = 4'b0001; com = 3'b010;
    #1 m = 4'b0001; n = 4'b0001; com = 3'b011;
    #1 m = 4'b0001; n = 4'b0001; com = 3'b100;
    #1 m = 4'b0001; n = 4'b0001; com = 3'b101;
    #1 m = 4'b1000; n = 4'b1000; com = 3'b110;
    #1 m = 4'b0001; n = 4'b0001; com = 3'b111;
end

initial 
    #21 $finish;

initial begin
   $dumpfile("ALUE03_tb.vcd");
   $dumpvars(0, testbench); 
end
endmodule

ALU/ALUE03_tb.vcd
$date
	Sun Oct 25 00:19:26 2020
$end
$version
	Icarus Verilog
$end
$timescale
	1ps
$end
$scope module testbench $end
$var wire 4 ! r [3:0] $end
$var reg 3 " com [2:0] $end
$var reg 4 # m [3:0] $end
$var reg 4 $ n [3:0] $end
$scope module test $end
$var wire 3 % com [2:0] $end
$var wire 4 & m [3:0] $end
$var wire 4 ' n [3:0] $end
$var reg 4 ( r [3:0] $end
$upscope $end
$upscope $end
$enddefinitions $end
#0
$dumpvars
bx (
bx '
bx &
bx %
bx $
bx #
bx "
bx !
$end
#1
b0 !
b0 (
b0 "
b0 %
b0 $
b0 '
b0 #
b0 &
#2
b1 !
b1 (
b1 $
b1 '
b1 #
b1 &
#3
b1 "
b1 %
#4
b10 !
b10 (
b10 "
b10 %
#5
b0 !
b0 (
b11 "
b11 %
#6
b100 "
b100 %
#7
b1111 !
b1111 (
b101 "
b101 %
#8
b0 !
b0 (
b110 "
b110 %
b1000 $
b1000 '
b1000 #
b1000 &
#9
b111 "
b111 %
b1 $
b1 '
b1 #
b1 &
